{
    "uuid": [
        {
            "value": "86353e7b-16c9-4889-98bb-941ef0c5cbfe"
        }
    ],
    "langcode": [
        {
            "value": "en"
        }
    ],
    "type": [
        {
            "target_id": "page",
            "target_type": "node_type",
            "target_uuid": "2840d8fd-b9e4-4e6e-837e-d2850cc82f50"
        }
    ],
    "revision_timestamp": [
        {
            "value": "2023-01-06T01:49:55+00:00",
            "format": "Y-m-d\\TH:i:sP"
        }
    ],
    "revision_uid": [
        {
            "target_type": "user",
            "target_uuid": "41ab6e92-3d00-440b-b92a-02910ddcf341"
        }
    ],
    "revision_log": [],
    "status": [
        {
            "value": true
        }
    ],
    "uid": [
        {
            "target_type": "user",
            "target_uuid": "41ab6e92-3d00-440b-b92a-02910ddcf341"
        }
    ],
    "title": [
        {
            "value": "Who am I?"
        }
    ],
    "created": [
        {
            "value": "2023-01-06T01:28:20+00:00",
            "format": "Y-m-d\\TH:i:sP"
        }
    ],
    "changed": [
        {
            "value": "2023-01-07T04:51:04+00:00",
            "format": "Y-m-d\\TH:i:sP"
        }
    ],
    "promote": [
        {
            "value": false
        }
    ],
    "sticky": [
        {
            "value": false
        }
    ],
    "default_langcode": [
        {
            "value": true
        }
    ],
    "revision_translation_affected": [
        {
            "value": true
        }
    ],
    "path": [
        {
            "alias": "\/about",
            "langcode": "en",
            "pathauto": 0
        }
    ],
    "body": [
        {
            "value": "<p>To state the obvious, my name is Dave. Born &amp; bred in Meriden, CT, and still calling Connecticut home, I am a tech enthusiast whose interests include coastal living, Dave Matthews Band, all kinds of sports (<em>but especially the Red Sox, Patriots &amp; UConn Huskies<\/em>), my dog and <strong>most importantly<\/strong> my family.<\/p><p>At the University of Connecticut, I studied business and economics, and graduated with both a Bachelor of Arts and Bachelor of Science.<\/p>",
            "format": "rich_text",
            "summary": ""
        }
    ]
}